{
  "auth": {
    "locationappa6d54cd9": {
      "service": "Cognito",
      "providerPlugin": "awscloudformation",
      "dependsOn": [],
      "customAuth": false,
      "frontendAuthConfig": {
        "socialProviders": [],
        "usernameAttributes": [],
        "signupAttributes": [
          "EMAIL"
        ],
        "passwordProtectionSettings": {
          "passwordPolicyMinLength": 8,
          "passwordPolicyCharacters": []
        },
        "mfaConfiguration": "OFF",
        "mfaTypes": [
          "SMS"
        ],
        "verificationMechanisms": [
          "EMAIL"
        ]
      }
    }
  },
  "geo": {
    "mapf09fad5f": {
      "isDefault": true,
      "providerPlugin": "awscloudformation",
      "service": "Map",
      "mapStyle": "VectorEsriStreets",
      "accessType": "AuthorizedAndGuestUsers",
      "dependsOn": [
        {
          "category": "auth",
          "resourceName": "locationappa6d54cd9",
          "attributes": [
            "UserPoolId"
          ]
        }
      ]
    }
  }
}